Metadata-Version: 2.1
Name: odoo14-addon-intrastat-base
Version: 14.0.2.2.0
Summary: Base module for Intrastat reporting
Home-page: https://github.com/OCA/intrastat-extrastat
Author: ACSONE SA/NV, Akretion,Noviat,Odoo Community Association (OCA)
Author-email: support@odoo-community.org
License: AGPL-3
Platform: UNKNOWN
Classifier: Programming Language :: Python
Classifier: Framework :: Odoo
Classifier: Framework :: Odoo :: 14.0
Classifier: License :: OSI Approved :: GNU Affero General Public License v3
Requires-Python: >=3.6
Requires-Dist: odoo (<14.1dev,>=14.0a)
